[{"source": 0, "target": 44}, {"source": 0, "target": 70}, {"source": 0, "target": 82}, {"source": 1, "target": 15}, {"source": 1, "target": 20}, {"source": 1, "target": 42}, {"source": 1, "target": 47}, {"source": 2, "target": 22}, {"source": 2, "target": 76}, {"source": 7, "target": 45}, {"source": 7, "target": 59}, {"source": 7, "target": 71}, {"source": 7, "target": 86}, {"source": 8, "target": 28}, {"source": 8, "target": 60}, {"source": 10, "target": 65}, {"source": 10, "target": 74}, {"source": 10, "target": 93}, {"source": 12, "target": 38}, {"source": 12, "target": 67}, {"source": 15, "target": 20}, {"source": 15, "target": 42}, {"source": 15, "target": 47}, {"source": 16, "target": 55}, {"source": 17, "target": 56}, {"source": 18, "target": 34}, {"source": 19, "target": 46}, {"source": 20, "target": 42}, {"source": 20, "target": 47}, {"source": 22, "target": 76}, {"source": 28, "target": 60}, {"source": 29, "target": 61}, {"source": 31, "target": 89}, {"source": 32, "target": 90}, {"source": 35, "target": 95}, {"source": 36, "target": 96}, {"source": 38, "target": 67}, {"source": 39, "target": 97}, {"source": 42, "target": 47}, {"source": 43, "target": 58}, {"source": 43, "target": 81}, {"source": 44, "target": 70}, {"source": 44, "target": 82}, {"source": 45, "target": 59}, {"source": 45, "target": 71}, {"source": 45, "target": 86}, {"source": 49, "target": 79}, {"source": 58, "target": 81}, {"source": 59, "target": 71}, {"source": 59, "target": 86}, {"source": 64, "target": 92}, {"source": 65, "target": 74}, {"source": 65, "target": 93}, {"source": 68, "target": 99}, {"source": 70, "target": 82}, {"source": 71, "target": 86}, {"source": 73, "target": 87}, {"source": 74, "target": 93}]